{
  "shortname": "portalrevolution",
  "version": "0.9.3",
  "game": "Portal Revolution",
  "basegame": "revolution",
  "steam_main_folder": "Portal Revolution",
  "max_chars_before_break": 45,
  "mod_type": "dlc",
  "dlc_compiler" : true,
  "os" : "WIN",
  "vpk_file_name": "pak01_dir.vpk",
  "other_files": [
    {"name": "subtitles","folder":"resource","localized": true,"override": false,"is_on_vpk": false, "translation_sheet": "subtitles","extension": "txt","dest_extension":"dat","is_captions": true,
      "encoding": "utf-16"}


  ],
  "vpk_output_folder": "portalrevolution_portl.vpk"

}